setup.py
pop_distributions/Binomialdistribution.py
pop_distributions/Gaussiandistribution.py
pop_distributions/Generaldistribution.py
pop_distributions/__init__.py
pop_distributions.egg-info/PKG-INFO
pop_distributions.egg-info/SOURCES.txt
pop_distributions.egg-info/dependency_links.txt
pop_distributions.egg-info/not-zip-safe
pop_distributions.egg-info/top_level.txt