Metadata-Version: 1.0
Name: pop-distributions
Version: 0.1
Summary: Gaussian and Binomial distributions
Home-page: UNKNOWN
Author: Nagaveda Reddy
Author-email: gajjalanagaveda@karunya.edu.in
License: UNKNOWN
Platform: UNKNOWN
